tap_oviond/__init__.py
tap_oviond/__main__.py
tap_oviond/client.py
tap_oviond/schemas/__init__.py
tap_oviond/streams.py
tap_oviond/tap.py
tap_oviond-0.0.9.dist-info/METADATA
tap_oviond-0.0.9.dist-info/WHEEL
tap_oviond-0.0.9.dist-info/entry_points.txt
tap_oviond-0.0.9.dist-info/RECORD
